{"created":"2015-05-13T15:42:55+00:00","modified":"2015-05-13T15:42:55+00:00","valid":{"from":"2011-07-20T10:00:00+00:00","to":"3011-07-20T10:00:00+00:00"},"hreflang":"en","guid":"00dbe051-f533-4894-889f-9453cc9f0695","byline":"Sarah Rainsford, John Dimsdale, Rob Schmitz, Peter van Dyk, Jeremy Hobson, Bob Moon, Gregory Warner and Steve Chiotakis","title":"Marketplace Morning Report for Wednesday, July 20, 2011","itags":["00dbe051f533894d89f89453cc9f0695","Marketplace","Marketplace Morning Report for Wednesday, July 20, 2011","PMP:Marketplace_PMP","Marketplace Morning Report"],"tags":["APM","APM_Episode"],"description":"Marketplace Morning Report for Wednesday, July 20, 2011","contenttemplated":"[]","published":"2011-07-20T10:00:00+00:00","contentencoded":"<div class=\"barn-cleaned\"></div>","teaser":"Marketplace Morning Report for Wednesday, July 20, 2011","audio":[{"type":"audio/mpeg","href":"http://play.publicradio.org/pmp/d/podcast/marketplace/morning_report/2011/07/20/marketplace_morning_report_full_20110720_64.mp3","format":"MP3","meta":{"duration":1302,"duration_hms":"00:21:42","api":{"href":"http://api.publicradio.org/audio/v2?ref=pmp&id=apm-audio:/marketplace/morning_report/2011/07/20/marketplace_morning_report_full_20110720","type":"application/json"}}}]}