{"created":"2015-04-03T17:09:15+00:00","modified":"2015-04-03T17:09:15+00:00","valid":{"from":"2015-04-03T17:09:15+00:00","to":"3015-04-03T17:09:15+00:00"},"hreflang":"en","guid":"23490654-51b4-4580-9eaf-8172408d2ecd","title":"The Limits Of Time In A Speedy World","published":"2014-11-17T21:15:00+00:00","teaser":"<p><em><em><em><em>[2014-11-17 13:00:00]</em></em></em></em><span style=\"font-family: Helvetica; font-size: xx-small;\"><span style=\"font-size: 12px; font-weight: normal; font-variant: normal;\"><span style=\"font-family: Calibri,sans-serif; font-size: small;\"><span style=\"font-size: 11pt;\"><span style=\"font-family: Gill Sans MT,sans-serif; font-size: large;\"><span style=\"font-size: 14pt;\"> Technological innovations are often designed to make tasks faster and more efficient. And yet it often feels like the more things quicken, the less time we actually have. This hour, we&#8217;ll talk about our culture&#8217;s need for speed and its effect on our well-being with Columbia University&#8217;s Mark C. Taylor, author of</span></span><span style=\"font-family: Gill Sans MT,sans-serif; font-size: large;\"><span style=\"font-size: 14pt;\">&#160;</span></span><span style=\"font-family: Gill Sans MT,sans-serif; font-size: large;\"><span style=\"font-size: 14pt;\"><em>Speed Limits: Where Time Went and Why We Have So Little Left.</em></span></span></span></span></span></span></p>","itags":["npr_api","364855707"],"contentencoded":"<p><div class=\"fullattribution\">Copyright 2015 MPX. To see more, visit <a href=\"\"></a>.<img src=\"http://www.google-analytics.com/__utm.gif?utmac=UA-5828686-4&utmdt=The+Limits+Of+Time+In+A+Speedy+World&utme=8(APIKey)9(MDAyOTcwNDAwMDEyODgyMDkwMTgwNzY3YQ001)\"/></div></p>","audio":[{"meta":{"duration":"2901"},"type":"audio/m3u","href":"http://api.npr.org/m3u/1364855711-0e2bea.m3u?orgId=30000&e=364855707&d=2901&ft=nprml&f=364855707"}]}