{"created":"2015-05-02T11:58:11+00:00","modified":"2015-05-10T15:05:22+00:00","valid":{"from":"2015-05-10T15:05:22+00:00","to":"3015-05-10T15:05:22+00:00"},"hreflang":"en","title":"A Boxing Match And A Derby: The Week In Sports","published":"2015-05-02T14:26:00+00:00","teaser":"NPR's Scott Simon and NPR's Tom Goldman chat about tonight's boxing match between Floyd Mayweather and Manny Pacquiao; the Kentucky Derby; and the NBA match-up between the Clippers and Spurs.","itags":["npr_api","403766898"],"guid":"42fb96a4-a589-4c95-8311-168663324221","contentencoded":"<p><div class=\"fullattribution\">Copyright 2015 NPR. To see more, visit <a href=\"http://www.npr.org/\">http://www.npr.org/</a>.<img src=\"http://www.google-analytics.com/__utm.gif?utmac=UA-5828686-4&utmdt=A+Boxing+Match+And+A+Derby%3A+The+Week+In+Sports&utme=8(APIKey)9(MDAyOTcwNDAwMDEyODgyMDkwMTgwNzY3YQ001)\"/></div></p>","audio":[{"meta":{"duration":"241"},"type":"audio/m3u","href":"http://api.npr.org/m3u/1403766899-4bd3d7.m3u?orgId=1&topicId=1055&d=241&p=7&story=403766898&t=progseg&e=403740101&seg=18&ft=nprml&f=403766898"}]}