{"created":"2015-05-20T16:00:24+00:00","modified":"2015-05-21T04:00:36+00:00","valid":{"from":"2015-05-20T06:00:00+00:00","to":"3015-05-20T06:00:00+00:00"},"hreflang":"en","teaser":"Wall Street eyes the fed, colleges may have to pay up for defaulted loans, and the costs of investing in a hedge fund.","tags":["APM","Life","Mid-day Update"],"contenttemplated":"[{\"type\":\"text/html\",\"content\":\"<p>How the head of the fed is keeping Wall Street workers chained to their desks ahead of the long holiday weekend. Plus, t<span>he Senate Education Committee meets Wednesday. Senator Lamar Alexander, who chairs the committee and is a former secretary of education, has proposed that colleges share in the risk of lending to student. He says this would lead to reduced student borrowing. </span><span>Ho</span><span>w would it work if colleges had “skin in the game” and </span><span>ho</span><span>w realistic is the proposal? </span><span>We&apos;ll also talk to Allan Sloan of the Washington Post about the costs of investing in a hedge fund.</span></p>\"}]","contentencoded":"<div class=\"barn-cleaned\"><p>How the head of the fed is keeping Wall Street workers chained to their desks ahead of the long holiday weekend. Plus, t<span>he Senate Education Committee meets Wednesday. Senator Lamar Alexander, who chairs the committee and is a former secretary of education, has proposed that colleges share in the risk of lending to student. He says this would lead to reduced student borrowing.&nbsp;</span><span>Ho</span><span>w would it work if colleges had “skin in the game” and&nbsp;</span><span>ho</span><span>w realistic is the proposal?&nbsp;</span><span>We'll also talk to Allan Sloan of the Washington Post about the costs of investing in a hedge fund.</span></p></div>","guid":"4ce00b6c-0fd0-4da8-869a-93c0c7bec57e","itags":["4ce00b6c0fd0da8869a493c0c7bec57e","Marketplace","Marketplace Morning Report","Marketplace Morning Report for Wednesday, May 20, 2015","PMP:Marketplace_PMP"],"published":"2015-05-20T06:00:00+00:00","description":"Wall Street eyes the fed, colleges may have to pay up for defaulted loans, and the costs of investing in a hedge fund.","byline":"David Brancaccio","title":"PODCAST: Skin in the game","audio":[{"href":"http://www.marketplace.org/sites/default/files/styles/primary-image-610x340/public/student-loan-debt.jpg?itok=X486uKSi","type":"image/jpeg","meta":{"width":"610","height":"340","crop":"primary"}},{"type":"audio/mpeg","href":"http://play.publicradio.org/pmp/d/podcast/marketplace/morning_report/2015/05/20/midday_20150520_pod_64.mp3","format":"MP3","meta":{"api":{"type":"application/json","href":"http://api.publicradio.org/audio/v2?ref=pmp&id=apm-audio:/marketplace/morning_report/2015/05/20/midday_20150520_pod"},"duration":398,"duration_hms":"00:06:38"}}]}