{"created":"2014-08-30T17:05:17+00:00","modified":"2014-10-30T23:12:05+00:00","valid":{"from":"2014-10-30T23:12:05+00:00","to":"3014-10-30T23:12:05+00:00"},"hreflang":"en","title":"Kurdish Forces Claim To Have Driven Militants From Dam","published":"2014-08-18T12:11:00+00:00","teaser":"A major dam in northern Iraq, near the city of Mosul, is the latest flashpoint. Kurdish officials say their forces have driven militants from the dam. The militants say they're fighting to hang on.","itags":["npr_api","341283354"],"guid":"8f54ec86-caaa-4561-bbf9-aaece89fe9ef","contentencoded":"<p><div class=\"fullattribution\">Copyright 2014 NPR. To see more, visit <a href=\"http://www.npr.org/\">http://www.npr.org/</a>.<img src=\"http://www.google-analytics.com/__utm.gif?utmac=UA-5828686-4&utmdt=Kurdish+Forces+Claim+To+Have+Driven+Militants+From+Dam&utme=8(APIKey)9(MDAyOTcwNDAwMDEyODgyMDkwMTgwNzY3YQ001)\"/></div></p>","byline":"Peter Kenyon","audio":[{"meta":{"duration":"204"},"type":"audio/m3u","href":"http://api.npr.org/m3u/1341283355-fa7a81.m3u?orgId=1&topicId=1010&ft=3&f=341283354"}]}