{"created":"2015-02-28T21:56:11+00:00","modified":"2015-03-02T14:16:59+00:00","valid":{"from":"2015-03-02T14:16:59+00:00","to":"3015-03-02T14:16:59+00:00"},"hreflang":"en","title":"The Challenges Of Jury Selection In The Boston Marathon Bombing Trial","published":"2015-02-28T23:39:00+00:00","teaser":"Is it possible to find an impartial jury to serve in a high-profile trial? NPR's Arun Rath talks with jury consultant Karen Fleming-Ginn about the issues that come up during jury selection.","itags":["npr_api","389796950"],"guid":"90a5e2a3-123d-446c-9a62-0087cd045d11","contentencoded":"<p><div class=\"fullattribution\">Copyright 2015 NPR. To see more, visit <a href=\"http://www.npr.org/\">http://www.npr.org/</a>.<img src=\"http://www.google-analytics.com/__utm.gif?utmac=UA-5828686-4&utmdt=The+Challenges+Of+Jury+Selection+In+The+Boston+Marathon+Bombing+Trial&utme=8(APIKey)9(MDAyOTcwNDAwMDEyODgyMDkwMTgwNzY3YQ001)\"/></div></p>","audio":[{"meta":{"duration":"276"},"type":"audio/m3u","href":"http://api.npr.org/m3u/1389796951-8a3a12.m3u?orgId=1&topicId=1070&e=389796950&d=276&ft=nprml&f=389796950"}]}