{"created":"2015-05-11T20:42:37+00:00","modified":"2015-05-12T04:40:24+00:00","valid":{"from":"2015-05-12T04:40:24+00:00","to":"3015-05-12T04:40:24+00:00"},"hreflang":"en","title":"New Book Explores Bobby Fuller's Mysterious Death","published":"2015-05-12T01:00:00+00:00","teaser":"A new book tells the story of Bobby Fuller, who was best-known for the song \"I Fought the Law.\" He was a talented guitarist and producer who moved from El Paso, Texas, to LA. He was on the verge of his big break when his body was found in his car doused in gasoline. The Los Angeles police ruled it an accidental death.","itags":["npr_api","405955609"],"guid":"a0ff5322-47de-476c-a3a4-13118e381b33","contentencoded":"<p><div class=\"fullattribution\">Copyright 2015 NPR. To see more, visit <a href=\"http://www.npr.org/\">http://www.npr.org/</a>.<img src=\"http://www.google-analytics.com/__utm.gif?utmac=UA-5828686-4&utmdt=New+Book+Explores+Bobby+Fuller%27s+Mysterious+Death&utme=8(APIKey)9(MDAyOTcwNDAwMDEyODgyMDkwMTgwNzY3YQ001)\"/></div></p>","byline":"Alex Cohen","audio":[{"meta":{"duration":"352"},"type":"audio/m3u","href":"http://api.npr.org/m3u/1405955610-101499.m3u?orgId=1&topicId=1032&d=352&p=2&story=405955609&t=progseg&e=405936490&seg=20&ft=nprml&f=405955609"}]}