{"created":"2015-04-03T20:34:48+00:00","modified":"2015-04-03T20:34:48+00:00","valid":{"from":"2015-04-03T20:34:48+00:00","to":"3015-04-03T20:34:48+00:00"},"hreflang":"en","guid":"a612cce1-db71-46b1-a188-b37ce0b4a67d","title":"Roundtable On Cory Briggs, One Paseo, Women In Combat","published":"2015-02-27T19:19:00+00:00","teaser":"Prominent San Diego attorney Cory Briggs is involved in some real estate deals that some find questionable. The controversial One Paseo development in Carmel Valley sails through the San Diego City Council.  The Marine Corps is exploring whether women can take on combat roles.<img src=\"//feeds.feedburner.com/~r/kpbs/news/~4/_a3ylouMJ5g\" height=\"1\" width=\"1\" alt=\"\"/>","itags":["npr_api","389635740"],"contentencoded":"<p><div class=\"fullattribution\">Copyright 2015 MPX. To see more, visit <a href=\"\"></a>.<img src=\"http://www.google-analytics.com/__utm.gif?utmac=UA-5828686-4&utmdt=%0ARoundtable+On+Cory+Briggs%2C+One+Paseo%2C+Women+In+Combat%0A%0A%0A%0A&utme=8(APIKey)9(MDAyOTcwNDAwMDEyODgyMDkwMTgwNzY3YQ001)\"/></div></p>","audio":[{"meta":{"duration":null},"type":"audio/m3u","href":"http://api.npr.org/m3u/1389635744-6f250b.m3u?orgId=30000&e=389635740&ft=nprml&f=389635740"},{"meta":{"duration":null},"type":"audio/m3u","href":"http://api.npr.org/m3u/1389635748-fa7ea8.m3u?orgId=30000&e=389635740&ft=nprml&f=389635740"}]}