{"created":"2015-06-16T18:11:42+00:00","modified":"2015-06-24T20:03:12+00:00","valid":{"from":"2013-12-18T04:13:14+00:00","to":"3013-12-18T04:13:14+00:00"},"hreflang":"en","contenttemplated":"[{\"type\":\"text/html\",\"content\":\"<p>The cost of college keeps going up. But family earnings are staying the same. This is leading to an unsustainable situation for both colleges and would-be students.<br /><br /></p>\"},{\"type\":\"text/html\",\"content\":\"<br />\"},{\"type\":\"text/html\",\"content\":\"<p>Guest: <a href=\\\"http://www.marketplace.org/people/chris-farrell\\\">Chris Farrell,</a> APM economics editor.</p>\"},{\"type\":\"text/html\",\"content\":\"<br />\"}]","itags":["American RadioWorks","American RadioWorks 2013-12-17","a9ae99ada04c6bf4edf2af523cff2953"],"title":"College Un-Affordability","teaser":"The cost of college keeps going up. But family earnings are staying the same. This is leading to an unsustainable […]","tags":["APM"],"description":"The cost of college keeps going up. But family earnings are staying the same. This is leading to an unsustainable […]","byline":"W Pengine","guid":"a9ae99ad-a04c-46bf-8edf-af523cff2953","contentencoded":"<div class=\"barn-cleaned\"><p>The cost of college keeps going up. But family earnings are staying the same. This is leading to an unsustainable situation for both colleges and would-be students.<br />\n<br /></p>\n<br />\n<p>Guest: <a href=\"http://www.marketplace.org/people/chris-farrell\">Chris Farrell,</a> APM economics editor.</p>\n<br /></div>","published":"2013-12-18T04:13:14+00:00","audio":[{"format":"MP3","href":"http://play.publicradio.org/pmp/d/podcast/americanradioworks/2013/7_12_collegeunaffordability_128.mp3","meta":{"duration":814,"api":{"href":"http://api.publicradio.org/audio/v2?ref=pmp&id=apm_audio:/americanradioworks/2013/7_12_collegeunaffordability","type":"application/json"},"duration_hms":"00:13:34"},"type":"audio/mpeg"}]}