{"created":"2015-02-12T19:00:10+00:00","modified":"2015-05-14T16:08:58+00:00","valid":{"from":"2015-02-12T18:14:55+00:00","to":"3015-02-12T18:14:55+00:00"},"hreflang":"en","teaser":"<p dir=\"ltr\"><span><span>Airing on Thursday, Feb. 12, 2015: W</span>hat happens when your ship comes in, and there’s no one there to unload your goods? We look at the ripple effect of the West Coast port strike. Plus, the choices are shrinking when it comes to online flight and hotel booking services. Weeks after snapping up Travelocity, Expedia announced a $1.6 billion buyout of another competitor, Orbitz, and competing giant Priceline is buying up smaller brands like Kayak.&nbsp;Who’s&nbsp;</span>benefiting<span>&nbsp;from all this? Also, we look at the new $17.5 billion International Monetary Fund loan package given to Ukraine. \"It's a tough program, and it's not without risk,\" says the IMF chief.\n</span></p>\n&nbsp;","contenttemplated":"[]","guid":"aa6a8592-dbeb-4b87-8fea-24ed0568e3ea","itags":["Marketplace","aa6a8592dbebb872fea824ed0568e3ea","PMP:Marketplace_PMP","Marketplace for Thursday, Feb. 12, 2015"],"tags":["APM","APM_Episode"],"title":"Marketplace for Thursday, Feb. 12, 2015","contentencoded":"<div class=\"barn-cleaned\"></div>","published":"2015-02-12T18:14:55+00:00","description":"<p dir=\"ltr\"><span><span>Airing on Thursday, Feb. 12, 2015: W</span>hat happens when your ship comes in, and there’s no one there to unload your goods? We look at the ripple effect of the West Coast port strike. Plus, the choices are shrinking when it comes to online flight and hotel booking services. Weeks after snapping up Travelocity, Expedia announced a $1.6 billion buyout of another competitor, Orbitz, and competing giant Priceline is buying up smaller brands like Kayak.&nbsp;Who’s&nbsp;</span>benefiting<span>&nbsp;from all this? Also, we look at the new $17.5 billion International Monetary Fund loan package given to Ukraine. \"It's a tough program, and it's not without risk,\" says the IMF chief.\n</span></p>\n&nbsp;","byline":"Kai Ryssdal, Dan Weissmann, Gigi Douban, Stan Alcorn, Tommy Andres, Deepa Fernandes and Sally Herships","audio":[{"type":"image/jpeg","meta":{"width":"610","height":"340","crop":"primary"},"href":"http://www.marketplace.org/sites/default/files/styles/primary-image-610x340/public/450564126.jpg?itok=nIqYxJqx"},{"meta":{"api":{"href":"http://api.publicradio.org/audio/v2?ref=pmp&id=apm-audio:/marketplace/pm/2015/02/12/pm_20150212_1400","type":"application/json"},"duration":1740,"duration_hms":"00:29:00"},"href":"http://play.publicradio.org/pmp/d/podcast/marketplace/pm/2015/02/12/pm_20150212_1400_64.mp3","format":"MP3","type":"audio/mpeg"}]}