{"created":"2015-06-27T13:32:03+00:00","modified":"2015-06-29T19:55:22+00:00","valid":{"from":"2015-06-29T19:55:22+00:00","to":"3015-06-29T19:55:22+00:00"},"hreflang":"en","title":"Lightning Fill In The Blank","published":"2015-06-27T15:45:00+00:00","teaser":"All the news we couldn't fit anywhere else.","itags":["npr_api","418032038"],"guid":"c21177e7-5c9c-4580-995e-68e8980df94e","contentencoded":"<p><div class=\"fullattribution\">Copyright 2015 NPR. To see more, visit <a href=\"http://www.npr.org/\">http://www.npr.org/</a>.<img src=\"http://www.google-analytics.com/__utm.gif?utmac=UA-5828686-4&utmdt=Lightning+Fill+In+The+Blank&utme=8(APIKey)9(MDAyOTcwNDAwMDEyODgyMDkwMTgwNzY3YQ001)\"/></div></p>","audio":[{"meta":{"duration":"306"},"type":"audio/m3u","href":"http://api.npr.org/m3u/1418074363-a21df0.m3u?orgId=1&d=306&p=35&story=418032038&t=progseg&e=417795808&seg=7&ft=nprml&f=418032038"}]}