{"created":"2015-06-26T17:10:31+00:00","modified":"2015-06-26T17:10:31+00:00","valid":{"from":"2005-12-29T17:00:00+00:00","to":"3005-12-29T17:00:00+00:00"},"hreflang":"en","guid":"ea5a3ab3-2751-4cee-8bab-ea92dcbd2c0b","description":"Personal finance expert Chris Farrell previews the 2006 housing market with host Scott Jagow.","tags":["APM","Ask Money","Your Money"],"contentencoded":"<div class=\"barn-cleaned\">Personal finance expert Chris Farrell previews the 2006 housing market with host Scott</div>","contenttemplated":"[]","teaser":"Personal finance expert Chris Farrell previews the 2006 housing market with host Scott Jagow.","byline":"Scott Jagow","published":"2005-12-29T17:00:00+00:00","title":"Farrell on the housing market","itags":["Marketplace","Marketplace AM","Marketplace AM for December 29, 2005","PMP:Marketplace_PMP","ea5a3ab32751cee7bab8ea92dcbd2c0b"],"audio":[{"meta":{"height":"340","crop":"primary","width":"610"},"href":"http://www.marketplace.org/sites/default/files/styles/primary-image-610x340/public/WWW/data/images/repository_orig/2005/12/29/20051229_openhouse_gettyid53062365.jpg?itok=79PC7Yz4","type":"image/jpeg"},{"type":"audio/mpeg","format":"MP3","meta":{"duration_hms":null,"duration":0,"api":{"href":"http://api.publicradio.org/audio/v2?ref=pmp&id=apm-audio:/marketplace/morning_report/2005/12/29_mktmorn0450","type":"application/json"}},"href":"http://play.publicradio.org/pmp/d/podcast/marketplace/morning_report/2005/12/29_mktmorn0450_128.mp3"},{"meta":{"api":{"href":"http://api.publicradio.org/audio/v2?ref=pmp&id=apm-audio:/marketplace/morning_report/2005/12/29_mktmorn0450","type":"application/json"},"duration_hms":null,"duration":0},"href":"http://play.publicradio.org/pmp/d/podcast/marketplace/morning_report/2005/12/29_mktmorn0450_128.mp3","type":"audio/mpeg","format":"MP3"}]}