{"created":"2015-03-04T18:00:26+00:00","modified":"2015-05-14T15:53:31+00:00","valid":{"from":"2015-03-04T12:00:00+00:00","to":"3015-03-04T12:00:00+00:00"},"hreflang":"en","tags":["APM","Mid-day Update","Life"],"published":"2015-03-04T12:00:00+00:00","teaser":"Looking ahead to the jobs report, Ukraine's interest rates, and the rise of gas prices.","guid":"f1ce5b1c-faee-4d23-8c2e-e10ad18b68f8","contentencoded":"<div class=\"barn-cleaned\"><p>First up, we'll talk about what the jobs report is likely to look like on Friday. Plus,&nbsp;<span>Ukraine’s central bank&nbsp;is raising its interest rate from 19.5 percent to 30 percent. The hike comes as the government is seeking a $17.5 billion assistance program from the International Monetary Fund. Inflation is rampant and the national currency has tumbled since Russia annexed Ukraine's southern Crimea peninsula and pro-Russian separatists took up arms in the country's east. &nbsp;We look at the reasons behind the hike in the interest rate. And g</span><span>as prices sure seem to go up a lot faster than they go down. On the West Coast, 37 cents a gallon just last week. We explain.</span></p></div>","title":"PODCAST: A forecast to Friday's Jobs Report","description":"Looking ahead to the jobs report, Ukraine's interest rates, and the rise of gas prices.","contenttemplated":"[{\"type\":\"text/html\",\"content\":\"<p>First up, we&apos;ll talk about what the jobs report is likely to look like on Friday. Plus, <span>Ukraine’s central bank is raising its interest rate from 19.5 percent to 30 percent. The hike comes as the government is seeking a $17.5 billion assistance program from the International Monetary Fund. Inflation is rampant and the national currency has tumbled since Russia annexed Ukraine&apos;s southern Crimea peninsula and pro-Russian separatists took up arms in the country&apos;s east.  We look at the reasons behind the hike in the interest rate. And g</span><span>as prices sure seem to go up a lot faster than they go down. On the West Coast, 37 cents a gallon just last week. We explain.</span></p>\"}]","byline":"David Gura","itags":["f1ce5b1cfaeed23bc2efe10ad18b68f8","PMP:Marketplace_PMP","Marketplace Morning Report for Wednesday, March 4, 2015","Marketplace Morning Report","Marketplace"],"audio":[{"href":"http://www.marketplace.org/sites/default/files/styles/primary-image-610x340/public/134973530_3.jpg?itok=oymmFueJ","type":"image/jpeg","meta":{"height":"340","crop":"primary","width":"610"}},{"href":"http://play.publicradio.org/pmp/d/podcast/marketplace/podcast_nu/2015/03/04/midday_20150304_pod_nu_64.mp3","type":"audio/mpeg","meta":{"duration":377,"api":{"href":"http://api.publicradio.org/audio/v2?ref=pmp&id=apm-audio:/marketplace/podcast_nu/2015/03/04/midday_20150304_pod_nu","type":"application/json"},"duration_hms":"00:06:17"},"format":"MP3"}]}